reliabots/VennABERS.py
reliabots/__init__.py
reliabots/calibrutils.py
reliabots/icp.py
reliabots/ivap.py
reliabots/nc_measures.py
reliabots/xcp.py
reliabots-0.2.7.dist-info/LICENSE
reliabots-0.2.7.dist-info/METADATA
reliabots-0.2.7.dist-info/WHEEL
reliabots-0.2.7.dist-info/top_level.txt
reliabots-0.2.7.dist-info/RECORD
