Metadata-Version: 2.1
Name: reliabots
Version: 0.2.7
Summary: Improve the reliability of machine learning models with conformal prediction
Home-page: https://github.com/patpizio/reliabots
Author: Patrizio Giovannotti
Author-email: patrizio.giovannotti.2019@live.rhul.ac.uk
Project-URL: Bug Tracker, https://github.com/patpizio/reliabots/issues
Classifier: Programming Language :: Python :: 3
Classifier: License :: OSI Approved :: MIT License
Classifier: Operating System :: OS Independent
Requires-Python: >=3.6
License-File: LICENSE
Requires-Dist: numpy
Requires-Dist: scikit-learn
Requires-Dist: scipy
Requires-Dist: plotly >=4.14.3
Requires-Dist: kaleido >=0.2.1
Requires-Dist: pandas
Requires-Dist: nonconformist >=2.1.0
